LICENSE
MANIFEST.in
README.rst
requirements.txt
setup.py
gd.graph.egg-info/PKG-INFO
gd.graph.egg-info/SOURCES.txt
gd.graph.egg-info/dependency_links.txt
gd.graph.egg-info/entry_points.txt
gd.graph.egg-info/requires.txt
gd.graph.egg-info/top_level.txt
gd/graph/__init__.py
gd/graph/__main__.py
gd/graph/utils.py