Metadata-Version: 2.1
Name: gd.graph
Version: 0.1.1
Summary: Plotting Graphs in Geometry Dash.
Home-page: https://github.com/nekitdev/gd.graph
Author: nekitdev
Author-email: nekitdevofficial@gmail.com
License: MIT
Project-URL: Issue tracker, https://github.com/nekitdev/gd.graph/issues
Platform: UNKNOWN
Classifier: Development Status :: 4 - Beta
Classifier: License :: OSI Approved :: MIT License
Classifier: Programming Language :: Python :: 3.6
Classifier: Programming Language :: Python :: 3.7
Classifier: Programming Language :: Python :: 3.8
Classifier: Programming Language :: Python :: 3.9
Classifier: Programming Language :: Python :: 3.10
Classifier: Typing :: Typed
Classifier: Natural Language :: English
Classifier: Operating System :: OS Independent
Requires-Python: >=3.6
